falconer/__init__.py
falconer/data/__init__.py
falconer/data/daos/__init__.py
falconer/data/daos/abstract_dao.py
falconer/system/__init__.py
falconer/system/dao_transaction_middleware.py
falconer/system/require_json_middleware.py
falconer/utils/__init__.py
falconer/utils/falcon_exceptions.py
falconer-0.2.8.dist-info/DESCRIPTION.rst
falconer-0.2.8.dist-info/METADATA
falconer-0.2.8.dist-info/metadata.json
falconer-0.2.8.dist-info/RECORD
falconer-0.2.8.dist-info/top_level.txt
falconer-0.2.8.dist-info/WHEEL
