Metadata-Version: 2.0
Name: falconer
Version: 0.2.8
Summary: fill this in
Home-page: https://github.com/sgiroux/falconer
Author: Sam Giroux, Ben Rabidou
Author-email: giroux@gmail.com
License: MIT
Keywords: Falcon Utility Framework
Platform: UNKNOWN
Classifier: Development Status :: 4 - Beta
Classifier: Intended Audience :: Developers
Classifier: Topic :: Software Development :: Libraries :: Python Modules
Classifier: License :: OSI Approved :: MIT License
Classifier: Programming Language :: Python :: 2
Classifier: Programming Language :: Python :: 2.6
Classifier: Programming Language :: Python :: 2.7
Classifier: Programming Language :: Python :: 3
Classifier: Programming Language :: Python :: 3.2
Classifier: Programming Language :: Python :: 3.3
Classifier: Programming Language :: Python :: 3.4
Requires-Dist: falcon
Requires-Dist: sqlalchemy
